intersight_rest/__init__.py
intersight_rest/intersight_rest.py
intersight_rest-1.1.7.dist-info/LICENSE.txt
intersight_rest-1.1.7.dist-info/METADATA
intersight_rest-1.1.7.dist-info/RECORD
intersight_rest-1.1.7.dist-info/WHEEL
intersight_rest-1.1.7.dist-info/top_level.txt
