Metadata-Version: 2.1
Name: intersight-rest
Version: 1.1.7
Summary: Cisco Intersight Python REST Module
Home-page: https://github.com/CiscoUcs/intersight-rest
Author: Matthew Garrett
Author-email: matgarre@cisco.com
License: UNKNOWN
Platform: UNKNOWN
Classifier: Programming Language :: Python :: 3
Classifier: Operating System :: OS Independent
Requires-Dist: six (>=1.11.0)
Requires-Dist: pycryptodome (>=3.6.4)
Requires-Dist: pycryptodomex (>=3.6.4)
Requires-Dist: requests (>=2.18.4)
